partinstall/__init__.py
partinstall/base_test.py
partinstall/hello.py
partinstall/array/__init__.py
partinstall/array/array_test.py
partinstall/dataframe/__init__.py
partinstall/dataframe/dataframe_test.py
partinstall-0.0.0.3.dist-info/METADATA
partinstall-0.0.0.3.dist-info/WHEEL
partinstall-0.0.0.3.dist-info/top_level.txt
partinstall-0.0.0.3.dist-info/RECORD
